{
    "instaloader": {
        "node_type": "Post",
        "version": "4.2.10"
    },
    "node": {
        "__typename": "GraphImage",
        "accessibility_caption": "Image may contain: 1 person",
        "caption_is_edited": false,
        "commenting_disabled_for_viewer": false,
        "comments_disabled": false,
        "dimensions": {
            "height": 722,
            "width": 1080
        },
        "display_resources": [
            {
                "config_height": 427,
                "config_width": 640,
                "src": "https://instagram.ftpe7-2.fna.fbcdn.net/v/t51.2885-15/sh0.08/e35/s640x640/23279506_480350809018019_3180293505956184064_n.jpg?_nc_ht=instagram.ftpe7-2.fna.fbcdn.net&_nc_cat=111&_nc_ohc=Vo4iCuC8Rk0AX_ZWCNa&oh=95c4519b75493ad0f3d8dece1bf186c3&oe=5E9CF133"
            },
            {
                "config_height": 501,
                "config_width": 750,
                "src": "https://instagram.ftpe7-2.fna.fbcdn.net/v/t51.2885-15/sh0.08/e35/s750x750/23279506_480350809018019_3180293505956184064_n.jpg?_nc_ht=instagram.ftpe7-2.fna.fbcdn.net&_nc_cat=111&_nc_ohc=Vo4iCuC8Rk0AX_ZWCNa&oh=9692c5e089cea75b8c1d13eb365fe898&oe=5EA23333"
            },
            {
                "config_height": 722,
                "config_width": 1080,
                "src": "https://instagram.ftpe7-2.fna.fbcdn.net/v/t51.2885-15/e35/23279506_480350809018019_3180293505956184064_n.jpg?_nc_ht=instagram.ftpe7-2.fna.fbcdn.net&_nc_cat=111&_nc_ohc=Vo4iCuC8Rk0AX_ZWCNa&oh=ff64bd972fa9e6276d4c66b611f0ad6f&oe=5E9A8FD6"
            }
        ],
        "display_url": "https://instagram.ftpe7-2.fna.fbcdn.net/v/t51.2885-15/e35/23279506_480350809018019_3180293505956184064_n.jpg?_nc_ht=instagram.ftpe7-2.fna.fbcdn.net&_nc_cat=111&_nc_ohc=Vo4iCuC8Rk0AX_ZWCNa&oh=ff64bd972fa9e6276d4c66b611f0ad6f&oe=5E9A8FD6",
        "edge_media_preview_comment": {
            "count": 11,
            "edges": [
                {
                    "node": {
                        "created_at": 1510157675,
                        "did_report_as_spam": false,
                        "edge_liked_by": {
                            "count": 0
                        },
                        "id": "17877831565168739",
                        "is_restricted_pending": false,
                        "owner": {
                            "id": "1543896377",
                            "is_verified": false,
                            "profile_pic_url": "https://instagram.ftpe7-4.fna.fbcdn.net/v/t51.2885-19/s150x150/89043063_500718157549825_6111602157125894144_n.jpg?_nc_ht=instagram.ftpe7-4.fna.fbcdn.net&_nc_ohc=BF85gsOuH_QAX-s50Dj&oh=445d792043965ce0b8be6d0c44de07c1&oe=5EA66AC8",
                            "username": "alisaj_1105"
                        },
                        "text": "@barry_1115 \u7d66\u4f60\u4e00\u5c0d\u7fc5\u8180",
                        "viewer_has_liked": false
                    }
                },
                {
                    "node": {
                        "created_at": 1510228246,
                        "did_report_as_spam": false,
                        "edge_liked_by": {
                            "count": 0
                        },
                        "id": "17881175605180531",
                        "is_restricted_pending": false,
                        "owner": {
                            "id": "3250350058",
                            "is_verified": false,
                            "profile_pic_url": "https://instagram.ftpe7-4.fna.fbcdn.net/v/t51.2885-19/s150x150/88129996_207767783934125_3287283155639205888_n.jpg?_nc_ht=instagram.ftpe7-4.fna.fbcdn.net&_nc_ohc=TBkRt6kgtoAAX-zQYyk&oh=5be3550bd02906d26810fb895ba7600e&oe=5EA74932",
                            "username": "menhera_lwd21"
                        },
                        "text": "\u6211\u5230\u73fe\u5728\u624d\u77e5\u9053\u6211\u8ddf\u59b3\u5dee\u5169\u6b72\ud83d\ude02",
                        "viewer_has_liked": false
                    }
                }
            ]
        },
        "edge_media_preview_like": {
            "count": 187,
            "edges": [
                {
                    "node": {
                        "id": "550394031",
                        "is_verified": false,
                        "profile_pic_url": "https://instagram.ftpe7-4.fna.fbcdn.net/v/t51.2885-19/s150x150/89455285_194249708676072_5996875596305530880_n.jpg?_nc_ht=instagram.ftpe7-4.fna.fbcdn.net&_nc_ohc=uZR0gB-6LPwAX_sI4sa&oh=bef0de353c03b0426b861d1dc4a328d0&oe=5EA71F85",
                        "username": "thursday7_uni"
                    }
                }
            ]
        },
        "edge_media_to_caption": {
            "edges": [
                {
                    "node": {
                        "text": "20171105\n\n\u665a\u4e86\u597d\u5e7e\u5929\n\u56e0\u70ba\u4e0d\u77e5\u9053\u8981\u767c\u4ec0\u9ebc\n\n\u50cf\u662f\u9084\u6c92\u6e96\u5099\u597d\u63a5\u53d7\u9019\u500b\u5e74\u9f61\u4e00\u6a23\n\n18\u4e0d\u50cf18\n\n\u671f\u8a31\u81ea\u5df1\u53ef\u4ee5\u6210\u719f\u4e9b\n\u5c0d\u7684\u4e0a\u9019\u500b\u6578\u5b57\n\u2661"
                    }
                }
            ]
        },
        "edge_media_to_comment": {
            "count": 11
        },
        "edge_media_to_hoisted_comment": {
            "edges": []
        },
        "edge_media_to_parent_comment": {
            "count": 11,
            "edges": [
                {
                    "node": {
                        "created_at": 1510147229,
                        "did_report_as_spam": false,
                        "edge_liked_by": {
                            "count": 0
                        },
                        "edge_threaded_comments": {
                            "count": 1,
                            "edges": [
                                {
                                    "node": {
                                        "created_at": 1510157625,
                                        "did_report_as_spam": false,
                                        "edge_liked_by": {
                                            "count": 0
                                        },
                                        "id": "17882583484156055",
                                        "is_restricted_pending": false,
                                        "owner": {
                                            "id": "1543896377",
                                            "is_verified": false,
                                            "profile_pic_url": "https://instagram.ftpe7-4.fna.fbcdn.net/v/t51.2885-19/s150x150/89043063_500718157549825_6111602157125894144_n.jpg?_nc_ht=instagram.ftpe7-4.fna.fbcdn.net&_nc_ohc=BF85gsOuH_QAX-s50Dj&oh=445d792043965ce0b8be6d0c44de07c1&oe=5EA66AC8",
                                            "username": "alisaj_1105"
                                        },
                                        "text": "@channel_1313 \u770b\u4e86\u662f\u7121\u6cd5\u4e86",
                                        "viewer_has_liked": false
                                    }
                                }
                            ],
                            "page_info": {
                                "end_cursor": null,
                                "has_next_page": false
                            }
                        },
                        "id": "17900658475067536",
                        "is_restricted_pending": false,
                        "owner": {
                            "id": "3945320541",
                            "is_verified": false,
                            "profile_pic_url": "https://instagram.ftpe7-4.fna.fbcdn.net/v/t51.2885-19/s150x150/83002955_177257936845424_3820329940427997184_n.jpg?_nc_ht=instagram.ftpe7-4.fna.fbcdn.net&_nc_ohc=K1MLyketr78AX_9mELT&oh=ce2aa2e8f6da622fbbf8a80d60346453&oe=5E9A84B7",
                            "username": "channel_1313"
                        },
                        "text": "\u8eab\u9ad8\u9019\u500b\u90e8\u5206\ud83d\ude06\ud83d\ude06",
                        "viewer_has_liked": false
                    }
                },
                {
                    "node": {
                        "created_at": 1510150551,
                        "did_report_as_spam": false,
                        "edge_liked_by": {
                            "count": 0
                        },
                        "edge_threaded_comments": {
                            "count": 1,
                            "edges": [
                                {
                                    "node": {
                                        "created_at": 1510157640,
                                        "did_report_as_spam": false,
                                        "edge_liked_by": {
                                            "count": 1
                                        },
                                        "id": "17908019221000769",
                                        "is_restricted_pending": false,
                                        "owner": {
                                            "id": "1543896377",
                                            "is_verified": false,
                                            "profile_pic_url": "https://instagram.ftpe7-4.fna.fbcdn.net/v/t51.2885-19/s150x150/89043063_500718157549825_6111602157125894144_n.jpg?_nc_ht=instagram.ftpe7-4.fna.fbcdn.net&_nc_ohc=BF85gsOuH_QAX-s50Dj&oh=445d792043965ce0b8be6d0c44de07c1&oe=5EA66AC8",
                                            "username": "alisaj_1105"
                                        },
                                        "text": "@andy.jen_1023 QQQQq",
                                        "viewer_has_liked": false
                                    }
                                }
                            ],
                            "page_info": {
                                "end_cursor": null,
                                "has_next_page": false
                            }
                        },
                        "id": "17910222880031191",
                        "is_restricted_pending": false,
                        "owner": {
                            "id": "1635256012",
                            "is_verified": false,
                            "profile_pic_url": "https://instagram.ftpe7-4.fna.fbcdn.net/v/t51.2885-19/s150x150/36800921_2023410701024766_7506082118632472576_n.jpg?_nc_ht=instagram.ftpe7-4.fna.fbcdn.net&_nc_ohc=yYdUq0WtGuUAX9wfPC5&oh=0d97805bac4de999e14d183cef0b18fa&oe=5E9AF939",
                            "username": "andy.jen_1023"
                        },
                        "text": "\u6c92\u4e8b\u5566\u6c92\u4e8b",
                        "viewer_has_liked": false
                    }
                },
                {
                    "node": {
                        "created_at": 1510151228,
                        "did_report_as_spam": false,
                        "edge_liked_by": {
                            "count": 0
                        },
                        "edge_threaded_comments": {
                            "count": 1,
                            "edges": [
                                {
                                    "node": {
                                        "created_at": 1510157656,
                                        "did_report_as_spam": false,
                                        "edge_liked_by": {
                                            "count": 0
                                        },
                                        "id": "17907147217003307",
                                        "is_restricted_pending": false,
                                        "owner": {
                                            "id": "1543896377",
                                            "is_verified": false,
                                            "profile_pic_url": "https://instagram.ftpe7-4.fna.fbcdn.net/v/t51.2885-19/s150x150/89043063_500718157549825_6111602157125894144_n.jpg?_nc_ht=instagram.ftpe7-4.fna.fbcdn.net&_nc_ohc=BF85gsOuH_QAX-s50Dj&oh=445d792043965ce0b8be6d0c44de07c1&oe=5EA66AC8",
                                            "username": "alisaj_1105"
                                        },
                                        "text": "@showchen1020 \u5e36\u8457\u9a55\u50b2\u7684\u7fc5\u8180\u98db\u9ad8\u9ad8",
                                        "viewer_has_liked": false
                                    }
                                }
                            ],
                            "page_info": {
                                "end_cursor": null,
                                "has_next_page": false
                            }
                        },
                        "id": "17901219922064214",
                        "is_restricted_pending": false,
                        "owner": {
                            "id": "1181340698",
                            "is_verified": false,
                            "profile_pic_url": "https://instagram.ftpe7-4.fna.fbcdn.net/v/t51.2885-19/s150x150/87633495_224037068775686_1486953588096761856_n.jpg?_nc_ht=instagram.ftpe7-4.fna.fbcdn.net&_nc_ohc=FP7VrviRDeUAX_HUBsE&oh=625a1f0207cbb6994c2d036e03f8338e&oe=5EA2DECF",
                            "username": "showchen5482"
                        },
                        "text": "\u5f9e\u5c0f\u6211\u6234\u8457\u9a55\u50b2\u7684\u7fc5\u8180",
                        "viewer_has_liked": false
                    }
                },
                {
                    "node": {
                        "created_at": 1510153112,
                        "did_report_as_spam": false,
                        "edge_liked_by": {
                            "count": 0
                        },
                        "edge_threaded_comments": {
                            "count": 1,
                            "edges": [
                                {
                                    "node": {
                                        "created_at": 1510157665,
                                        "did_report_as_spam": false,
                                        "edge_liked_by": {
                                            "count": 0
                                        },
                                        "id": "17905427746049119",
                                        "is_restricted_pending": false,
                                        "owner": {
                                            "id": "1543896377",
                                            "is_verified": false,
                                            "profile_pic_url": "https://instagram.ftpe7-4.fna.fbcdn.net/v/t51.2885-19/s150x150/89043063_500718157549825_6111602157125894144_n.jpg?_nc_ht=instagram.ftpe7-4.fna.fbcdn.net&_nc_ohc=BF85gsOuH_QAX-s50Dj&oh=445d792043965ce0b8be6d0c44de07c1&oe=5EA66AC8",
                                            "username": "alisaj_1105"
                                        },
                                        "text": "@yuboy0630 \u6c92\u6709\u554f\u984c!",
                                        "viewer_has_liked": false
                                    }
                                }
                            ],
                            "page_info": {
                                "end_cursor": null,
                                "has_next_page": false
                            }
                        },
                        "id": "17847837211209032",
                        "is_restricted_pending": false,
                        "owner": {
                            "id": "299831571",
                            "is_verified": false,
                            "profile_pic_url": "https://instagram.ftpe7-4.fna.fbcdn.net/v/t51.2885-19/s150x150/40696883_2188586478088157_2673301569037926400_n.jpg?_nc_ht=instagram.ftpe7-4.fna.fbcdn.net&_nc_ohc=dQnQ6CsSCxIAX_4SiLM&oh=aa7b43de02023d36a29f05deb761d10a&oe=5EA72501",
                            "username": "__yu0630"
                        },
                        "text": "\u8003\u99d5\u7167\u554a",
                        "viewer_has_liked": false
                    }
                },
                {
                    "node": {
                        "created_at": 1510155743,
                        "did_report_as_spam": false,
                        "edge_liked_by": {
                            "count": 0
                        },
                        "edge_threaded_comments": {
                            "count": 1,
                            "edges": [
                                {
                                    "node": {
                                        "created_at": 1510157675,
                                        "did_report_as_spam": false,
                                        "edge_liked_by": {
                                            "count": 0
                                        },
                                        "id": "17877831565168739",
                                        "is_restricted_pending": false,
                                        "owner": {
                                            "id": "1543896377",
                                            "is_verified": false,
                                            "profile_pic_url": "https://instagram.ftpe7-4.fna.fbcdn.net/v/t51.2885-19/s150x150/89043063_500718157549825_6111602157125894144_n.jpg?_nc_ht=instagram.ftpe7-4.fna.fbcdn.net&_nc_ohc=BF85gsOuH_QAX-s50Dj&oh=445d792043965ce0b8be6d0c44de07c1&oe=5EA66AC8",
                                            "username": "alisaj_1105"
                                        },
                                        "text": "@barry_1115 \u7d66\u4f60\u4e00\u5c0d\u7fc5\u8180",
                                        "viewer_has_liked": false
                                    }
                                }
                            ],
                            "page_info": {
                                "end_cursor": null,
                                "has_next_page": false
                            }
                        },
                        "id": "17906535499012384",
                        "is_restricted_pending": false,
                        "owner": {
                            "id": "1667623525",
                            "is_verified": false,
                            "profile_pic_url": "https://instagram.ftpe7-4.fna.fbcdn.net/v/t51.2885-19/s150x150/72585514_747112119128010_2366796214415917056_n.jpg?_nc_ht=instagram.ftpe7-4.fna.fbcdn.net&_nc_ohc=epp7DnlWuLwAX-fByWl&oh=5d4a766b2662d467088a14c43a9bcc06&oe=5EA05557",
                            "username": "barryyrbs"
                        },
                        "text": "\u6211\u60f3\u8981\u7fc5\u8180\uff01",
                        "viewer_has_liked": false
                    }
                },
                {
                    "node": {
                        "created_at": 1510228246,
                        "did_report_as_spam": false,
                        "edge_liked_by": {
                            "count": 0
                        },
                        "edge_threaded_comments": {
                            "count": 0,
                            "edges": [],
                            "page_info": {
                                "end_cursor": null,
                                "has_next_page": false
                            }
                        },
                        "id": "17881175605180531",
                        "is_restricted_pending": false,
                        "owner": {
                            "id": "3250350058",
                            "is_verified": false,
                            "profile_pic_url": "https://instagram.ftpe7-4.fna.fbcdn.net/v/t51.2885-19/s150x150/88129996_207767783934125_3287283155639205888_n.jpg?_nc_ht=instagram.ftpe7-4.fna.fbcdn.net&_nc_ohc=TBkRt6kgtoAAX-zQYyk&oh=5be3550bd02906d26810fb895ba7600e&oe=5EA74932",
                            "username": "menhera_lwd21"
                        },
                        "text": "\u6211\u5230\u73fe\u5728\u624d\u77e5\u9053\u6211\u8ddf\u59b3\u5dee\u5169\u6b72\ud83d\ude02",
                        "viewer_has_liked": false
                    }
                }
            ],
            "page_info": {
                "end_cursor": null,
                "has_next_page": false
            }
        },
        "edge_media_to_sponsor_user": {
            "edges": []
        },
        "edge_media_to_tagged_user": {
            "edges": []
        },
        "edge_web_media_to_related_media": {
            "edges": []
        },
        "fact_check_information": null,
        "fact_check_overall_rating": null,
        "gating_info": null,
        "has_ranked_comments": false,
        "id": "1643553568898539764",
        "is_ad": false,
        "is_video": false,
        "location": null,
        "media_preview": "ACocyY+c/Q/yqCro8vJCHjHfr05PSo41jBO47hg4xkYPYnjp7UgKwqzMf3aDGPvdzxz+v40Lb7gSp3Y9AatSWpKr1yOvHr3AHp3/ADNFx2Mykq0kSk8Pz9CP508PABggE+vzUCK8Z5/A/wAqYBTk61q6fZxzozPnK9MHHagCokpiBYcZH5fSgXDDbzjI5qvKaY5zj2ApWNG7aEpiAYKTgGjyV9T+VKDlR7GjNMlrU//Z",
        "owner": {
            "biography": "\u0274\u1d1b\u1d1c\u0299 \u1d00\u1d04\u1d04\n\ud835\udff7\ud835\udfff\ud835\udfff\ud835\udfff \u2740",
            "blocked_by_viewer": false,
            "business_category_name": null,
            "category_id": null,
            "connected_fb_page": null,
            "country_block": false,
            "edge_felix_video_timeline": {
                "count": 0,
                "edges": [],
                "page_info": {
                    "end_cursor": null,
                    "has_next_page": false
                }
            },
            "edge_follow": {
                "count": 638
            },
            "edge_followed_by": {
                "count": 732
            },
            "edge_mutual_followed_by": {
                "count": 8,
                "edges": [
                    {
                        "node": {
                            "username": "you_chi_890816"
                        }
                    },
                    {
                        "node": {
                            "username": "danny_o626"
                        }
                    },
                    {
                        "node": {
                            "username": "mometun_2379"
                        }
                    }
                ]
            },
            "external_url": null,
            "external_url_linkshimmed": null,
            "followed_by_viewer": true,
            "follows_viewer": true,
            "full_name": "Alisa \ud83e\udd40\ud83e\udd40",
            "has_ar_effects": false,
            "has_blocked_viewer": false,
            "has_channel": false,
            "has_requested_viewer": false,
            "highlight_reel_count": 7,
            "id": "1543896377",
            "is_business_account": false,
            "is_joined_recently": false,
            "is_private": true,
            "is_verified": false,
            "overall_category_name": null,
            "profile_pic_url": "https://instagram.ftpe7-4.fna.fbcdn.net/v/t51.2885-19/s150x150/89043063_500718157549825_6111602157125894144_n.jpg?_nc_ht=instagram.ftpe7-4.fna.fbcdn.net&_nc_ohc=BF85gsOuH_QAX-s50Dj&oh=445d792043965ce0b8be6d0c44de07c1&oe=5EA66AC8",
            "profile_pic_url_hd": "https://instagram.ftpe7-4.fna.fbcdn.net/v/t51.2885-19/s320x320/89043063_500718157549825_6111602157125894144_n.jpg?_nc_ht=instagram.ftpe7-4.fna.fbcdn.net&_nc_ohc=BF85gsOuH_QAX-s50Dj&oh=01712fa8f666cb98e817ca085c06786d&oe=5E9D4638",
            "requested_by_viewer": false,
            "restricted_by_viewer": false,
            "username": "alisaj_1105"
        },
        "shortcode": "BbPE0NTheD0YQbaFrzrehj8xWWUizg8rdLyUUg0",
        "taken_at_timestamp": 1510146875,
        "thumbnail_resources": [
            {
                "config_height": 150,
                "config_width": 150,
                "src": "https://instagram.ftpe7-2.fna.fbcdn.net/v/t51.2885-15/e35/c179.0.722.722a/s150x150/23279506_480350809018019_3180293505956184064_n.jpg?_nc_ht=instagram.ftpe7-2.fna.fbcdn.net&_nc_cat=111&_nc_ohc=Vo4iCuC8Rk0AX_ZWCNa&oh=60ea25d5881b607a1c5898ebcebff027&oe=5EA1447B"
            },
            {
                "config_height": 240,
                "config_width": 240,
                "src": "https://instagram.ftpe7-2.fna.fbcdn.net/v/t51.2885-15/e35/c179.0.722.722a/s240x240/23279506_480350809018019_3180293505956184064_n.jpg?_nc_ht=instagram.ftpe7-2.fna.fbcdn.net&_nc_cat=111&_nc_ohc=Vo4iCuC8Rk0AX_ZWCNa&oh=3ac07cb20dfd1f95ec268a16f4fa5180&oe=5E9CA731"
            },
            {
                "config_height": 320,
                "config_width": 320,
                "src": "https://instagram.ftpe7-2.fna.fbcdn.net/v/t51.2885-15/e35/c179.0.722.722a/s320x320/23279506_480350809018019_3180293505956184064_n.jpg?_nc_ht=instagram.ftpe7-2.fna.fbcdn.net&_nc_cat=111&_nc_ohc=Vo4iCuC8Rk0AX_ZWCNa&oh=fa98abc4fb7753348deadec1e876f0b2&oe=5EA0538B"
            },
            {
                "config_height": 480,
                "config_width": 480,
                "src": "https://instagram.ftpe7-2.fna.fbcdn.net/v/t51.2885-15/e35/c179.0.722.722a/s480x480/23279506_480350809018019_3180293505956184064_n.jpg?_nc_ht=instagram.ftpe7-2.fna.fbcdn.net&_nc_cat=111&_nc_ohc=Vo4iCuC8Rk0AX_ZWCNa&oh=cd2d60d64dd70cdd2fb82df82cb68844&oe=5EA1BDD1"
            },
            {
                "config_height": 640,
                "config_width": 640,
                "src": "https://instagram.ftpe7-2.fna.fbcdn.net/v/t51.2885-15/sh0.08/e35/c179.0.722.722a/s640x640/23279506_480350809018019_3180293505956184064_n.jpg?_nc_ht=instagram.ftpe7-2.fna.fbcdn.net&_nc_cat=111&_nc_ohc=Vo4iCuC8Rk0AX_ZWCNa&oh=a0863cc396f82dc94438c3a622b5eca2&oe=5EA0FF13"
            }
        ],
        "thumbnail_src": "https://instagram.ftpe7-2.fna.fbcdn.net/v/t51.2885-15/sh0.08/e35/c179.0.722.722a/s640x640/23279506_480350809018019_3180293505956184064_n.jpg?_nc_ht=instagram.ftpe7-2.fna.fbcdn.net&_nc_cat=111&_nc_ohc=Vo4iCuC8Rk0AX_ZWCNa&oh=a0863cc396f82dc94438c3a622b5eca2&oe=5EA0FF13",
        "tracking_token": "eyJ2ZXJzaW9uIjo1LCJwYXlsb2FkIjp7ImlzX2FuYWx5dGljc190cmFja2VkIjpmYWxzZSwidXVpZCI6IjRjMGRmNDA4NzIyNjRhMTJhN2U3YWQzOTI5ZTEyZTlmMTY0MzU1MzU2ODg5ODUzOTc2NCIsInNlcnZlcl90b2tlbiI6IjE1ODQzNTc5MzAzNjd8MTY0MzU1MzU2ODg5ODUzOTc2NHwxNjIwNjY5MTQ5fDcyYWI0ZGY3MWUyYzk0NWUzNjUwZDEyZjE4MDg3MGM5ZTI4NDFjOGY0ODExYzY2NTdkMWU2OTJlZWFjYjgxODcifSwic2lnbmF0dXJlIjoiIn0=",
        "viewer_can_reshare": true,
        "viewer_has_liked": false,
        "viewer_has_saved": false,
        "viewer_has_saved_to_collection": false,
        "viewer_in_photo_of_you": false
    }
}