[
    {
        "id": 17946977053134916,
        "created_at": 1535298315,
        "text": "Love U",
        "owner": {
            "id": "1512322793",
            "is_verified": false,
            "profile_pic_url": "https://instagram.ftpe7-4.fna.fbcdn.net/v/t51.2885-19/s150x150/79645456_710025752867327_2146352701506584576_n.jpg?_nc_ht=instagram.ftpe7-4.fna.fbcdn.net&_nc_ohc=VMyj6vrsGXIAX9JYZ0J&oh=6d2a0dd1a5b2b55b34871ca5f89f1a75&oe=5EA603D3",
            "username": "purple_shan"
        },
        "likes_count": 0,
        "answers": [
            {
                "id": 17973168859013958,
                "created_at": 1535298337,
                "text": "@purple_shan \u5641\u5fc3\uff08x",
                "owner": {
                    "id": "1543896377",
                    "is_verified": false,
                    "profile_pic_url": "https://instagram.ftpe7-4.fna.fbcdn.net/v/t51.2885-19/s150x150/89043063_500718157549825_6111602157125894144_n.jpg?_nc_ht=instagram.ftpe7-4.fna.fbcdn.net&_nc_ohc=BF85gsOuH_QAX-s50Dj&oh=445d792043965ce0b8be6d0c44de07c1&oe=5EA66AC8",
                    "username": "alisaj_1105"
                },
                "likes_count": 0
            }
        ]
    }
]